blog_manage/__init__.py
blog_manage/cli.py
blog_manage/utils.py
blog_manage-0.2.0.dist-info/METADATA
blog_manage-0.2.0.dist-info/WHEEL
blog_manage-0.2.0.dist-info/entry_points.txt
blog_manage-0.2.0.dist-info/licenses/LICENSE.txt
blog_manage-0.2.0.dist-info/RECORD
