Metadata-Version: 2.4
Name: blog-manage
Version: 0.2.0
Summary: Add your description here
Author-email: shizukani-cp <shizukani.cp@gmail.com>
License-File: LICENSE.txt
Requires-Python: >=3.8
Requires-Dist: jinja2>=3.1.4
Requires-Dist: markdown>=3.7
Requires-Dist: pyyaml>=6.0.2
